sources/__init__.py
sources/function1.py
pytestfcc-0.1.0.dist-info/METADATA
pytestfcc-0.1.0.dist-info/WHEEL
pytestfcc-0.1.0.dist-info/RECORD
