Metadata-Version: 2.1
Name: pytestfcc
Version: 0.1.0
Summary: i test cicd with github_action
Author: wtayo
Author-email: wtayo@ippon.fr
Requires-Python: >=3.11,<4.0
Classifier: Programming Language :: Python :: 3
Classifier: Programming Language :: Python :: 3.11
Classifier: Programming Language :: Python :: 3.12
